xasdesbotapi/__init__.py
xasdesbotapi/xasdesbotapi.py
xasdesbotapi-0.1.dist-info/METADATA
xasdesbotapi-0.1.dist-info/WHEEL
xasdesbotapi-0.1.dist-info/top_level.txt
xasdesbotapi-0.1.dist-info/RECORD
